{
    "pools": [
        {
            "rolls": 1,
            "entries": [
                {
                    "type": "item",
                    "name": "mts:warkparts.wark_wheel_64x16_black",
                    "weight": 5,
                    "functions": [
                        {
                            "function": "set_count",
                            "count": 2
                        }
                    ]
                },
                {
                    "type": "item",
                    "name": "mts:warkparts.wark_wheel_64x16_orange",
                    "weight": 5,
                    "functions": [
                        {
                            "function": "set_count",
                            "count": 2
                        }
                    ]
                },
                {
                    "type": "item",
                    "name": "mts:warkparts.wark_wheel_64x16_white",
                    "weight": 5,
                    "functions": [
                        {
                            "function": "set_count",
                            "count": 2
                        }
                    ]
                },
                {
                    "type": "item",
                    "name": "mts:warkparts.wark_wheel_64x16_yellow",
                    "weight": 5,
                    "functions": [
                        {
                            "function": "set_count",
                            "count": 2
                        }
                    ]
                },
                {
                    "type": "item",
                    "name": "mts:warkparts.wark_tractor_wheel_34x12_gray",
                    "weight": 5,
                    "functions": [
                        {
                            "function": "set_count",
                            "count": 2
                        }
                    ]
                },
                {
                    "type": "item",
                    "name": "mts:warkparts.wark_tractor_wheel_34x12_red",
                    "weight": 5,
                    "functions": [
                        {
                            "function": "set_count",
                            "count": 2
                        }
                    ]
                },
                {
                    "type": "item",
                    "name": "mts:warkparts.wark_tractor_wheel_34x12_yellow",
                    "weight": 5,
                    "functions": [
                        {
                            "function": "set_count",
                            "count": 2
                        }
                    ]
                },
                {
                    "type": "item",
                    "name": "mts:warkparts.wark_tractor_wheel_36x12_gray",
                    "weight": 5,
                    "functions": [
                        {
                            "function": "set_count",
                            "count": 2
                        }
                    ]
                },
                {
                    "type": "item",
                    "name": "mts:warkparts.wark_tractor_wheel_36x12_red",
                    "weight": 5,
                    "functions": [
                        {
                            "function": "set_count",
                            "count": 2
                        }
                    ]
                },
                {
                    "type": "item",
                    "name": "mts:warkparts.wark_tractor_wheel_36x12_yellow",
                    "weight": 5,
                    "functions": [
                        {
                            "function": "set_count",
                            "count": 2
                        }
                    ]
                },
                {
                    "type": "item",
                    "name": "mts:warkparts.wark_tractor_wheel_38x13_gray",
                    "weight": 5,
                    "functions": [
                        {
                            "function": "set_count",
                            "count": 2
                        }
                    ]
                },
                {
                    "type": "item",
                    "name": "mts:warkparts.wark_tractor_wheel_38x13_red",
                    "weight": 5,
                    "functions": [
                        {
                            "function": "set_count",
                            "count": 2
                        }
                    ]
                },
                {
                    "type": "item",
                    "name": "mts:warkparts.wark_tractor_wheel_38x13_yellow",
                    "weight": 5,
                    "functions": [
                        {
                            "function": "set_count",
                            "count": 2
                        }
                    ]
                },
                {
                    "type": "item",
                    "name": "mts:warkparts.wark_tractor_wheel_40x14_gray",
                    "weight": 5,
                    "functions": [
                        {
                            "function": "set_count",
                            "count": 2
                        }
                    ]
                },
                {
                    "type": "item",
                    "name": "mts:warkparts.wark_tractor_wheel_40x14_red",
                    "weight": 5,
                    "functions": [
                        {
                            "function": "set_count",
                            "count": 2
                        }
                    ]
                },
                {
                    "type": "item",
                    "name": "mts:warkparts.wark_tractor_wheel_40x14_yellow",
                    "weight": 5,
                    "functions": [
                        {
                            "function": "set_count",
                            "count": 2
                        }
                    ]
                },
                {
                    "type": "item",
                    "name": "mts:warkparts.wark_tractor_wheel_42x14_gray",
                    "weight": 5,
                    "functions": [
                        {
                            "function": "set_count",
                            "count": 2
                        }
                    ]
                },
                {
                    "type": "item",
                    "name": "mts:warkparts.wark_tractor_wheel_42x14_red",
                    "weight": 5,
                    "functions": [
                        {
                            "function": "set_count",
                            "count": 2
                        }
                    ]
                },
                {
                    "type": "item",
                    "name": "mts:warkparts.wark_tractor_wheel_42x14_yellow",
                    "weight": 5,
                    "functions": [
                        {
                            "function": "set_count",
                            "count": 2
                        }
                    ]
                },
                {
                    "type": "item",
                    "name": "mts:warkparts.wark_tractor_wheel_44x14_gray",
                    "weight": 5,
                    "functions": [
                        {
                            "function": "set_count",
                            "count": 2
                        }
                    ]
                },
                {
                    "type": "item",
                    "name": "mts:warkparts.wark_tractor_wheel_44x14_red",
                    "weight": 5,
                    "functions": [
                        {
                            "function": "set_count",
                            "count": 2
                        }
                    ]
                },
                {
                    "type": "item",
                    "name": "mts:warkparts.wark_tractor_wheel_44x14_yellow",
                    "weight": 5,
                    "functions": [
                        {
                            "function": "set_count",
                            "count": 2
                        }
                    ]
                },
                {
                    "type": "item",
                    "name": "mts:warkparts.wark_tractor_wheel_46x15_gray",
                    "weight": 5,
                    "functions": [
                        {
                            "function": "set_count",
                            "count": 2
                        }
                    ]
                },
                {
                    "type": "item",
                    "name": "mts:warkparts.wark_tractor_wheel_46x15_red",
                    "weight": 5,
                    "functions": [
                        {
                            "function": "set_count",
                            "count": 2
                        }
                    ]
                },
                {
                    "type": "item",
                    "name": "mts:warkparts.wark_tractor_wheel_46x15_yellow",
                    "weight": 5,
                    "functions": [
                        {
                            "function": "set_count",
                            "count": 2
                        }
                    ]
                },
                {
                    "type": "item",
                    "name": "mts:warkparts.wark_tractor_wheel_48x16_gray",
                    "weight": 5,
                    "functions": [
                        {
                            "function": "set_count",
                            "count": 2
                        }
                    ]
                },
                {
                    "type": "item",
                    "name": "mts:warkparts.wark_tractor_wheel_48x16_red",
                    "weight": 5,
                    "functions": [
                        {
                            "function": "set_count",
                            "count": 2
                        }
                    ]
                },
                {
                    "type": "item",
                    "name": "mts:warkparts.wark_tractor_wheel_48x16_yellow",
                    "weight": 5,
                    "functions": [
                        {
                            "function": "set_count",
                            "count": 2
                        }
                    ]
                }
            ]
        }
    ]
}