{
    "pools": [
        {
            "rolls": 1,
            "entries": [
                {
                    "type": "item",
                    "name": "mts:iv_tcp_v3_civil.trin_footpather_phase1_lemonyellow_g",
                    "weight": 5
                },
                {
                    "type": "item",
                    "name": "mts:iv_tcp_v3_civil.trin_footpather_phase1_orangered_g",
                    "weight": 5
                },
                {
                    "type": "item",
                    "name": "mts:iv_tcp_v3_civil.trin_footpather_phase1_sand_g",
                    "weight": 5
                },
                {
                    "type": "item",
                    "name": "mts:iv_tcp_v3_civil.trin_footpather_phase1_seafoam_g",
                    "weight": 5
                },
                {
                    "type": "item",
                    "name": "mts:iv_tcp_v3_civil.trin_footpather_phase1_teal_g",
                    "weight": 5
                },
                {
                    "type": "item",
                    "name": "mts:iv_tcp_v3_civil.trin_footpather_phase2_ivory_g",
                    "weight": 5
                },
                {
                    "type": "item",
                    "name": "mts:iv_tcp_v3_civil.trin_footpather_phase2_oceanblue_g",
                    "weight": 5
                },
                {
                    "type": "item",
                    "name": "mts:iv_tcp_v3_civil.trin_footpather_phase2_ruby_g",
                    "weight": 5
                },
                {
                    "type": "item",
                    "name": "mts:iv_tcp_v3_civil.trin_footpather_phase2_sage_g",
                    "weight": 5
                },
                {
                    "type": "item",
                    "name": "mts:iv_tcp_v3_civil.trin_footpather_phase2_sandstone_g",
                    "weight": 5
                },
                {
                    "type": "item",
                    "name": "mts:iv_tcp_v3_civil.trin_footpather_phase2_softgreen_g",
                    "weight": 5
                },
                {
                    "type": "item",
                    "name": "mts:iv_tcp_v3_civil.trin_footpather_phase2_steelblue_g",
                    "weight": 5
                }
            ]
        }
    ]
}