{
    "DialogShowWheel": 0b,
    "AvailabilityQuestId": -1,
    "Options": [
    ],
    "AvailabilityScoreboardType": 1,
    "DialogHideNPC": 0b,
    "AvailabilityFactionStance": 0,
    "AvailabilityScoreboard2Value": 1,
    "DialogId": 232,
    "AvailabilityQuest": 0,
    "AvailabilityDialog4": 0,
    "AvailabilityScoreboardObjective": "",
    "AvailabilityDialog3": 0,
    "AvailabilityQuest2": 0,
    "AvailabilityQuest3": 0,
    "AvailabilityScoreboard2Objective": "",
    "AvailabilityQuest4": 0,
    "ModRev": 18,
    "DecreaseFaction1Points": 0b,
    "DialogQuest": 59,
    "AvailabilityDialog2": 0,
    "OptionFactions1": -1,
    "AvailabilityDayTime": 0,
    "OptionFactions2": -1,
    "AvailabilityFaction2Id": -1,
    "OptionFaction1Points": 100,
    "AvailabilityScoreboardValue": 1,
    "DialogDisableEsc": 0b,
    "AvailabilityFaction": 0,
    "DialogTitle": "Officer Reynolds Conclusion 1",
    "AvailabilityDialog": 0,
    "AvailabilityScoreboard2Type": 1,
    "AvailabilityFaction2": 0,
    "AvailabilityFactionId": -1,
    "AvailabilityFaction2Stance": 0,
    "DialogCommand": "",
    "AvailabilityDialogId": -1,
    "OptionFaction2Points": 100,
    "DialogText": "You’ve more than helped—you’ve proven yourself capable of handling difficult situations with professionalism and care. Because of your exemplary performance, I’m happy to inform you that your application for the Personal Defense Permit (PDP) has been approved. Congratulations, you’ve earned it.

Keep up the good work, @p. We need more people like you looking out for this community. And remember, the PDP is a responsibility as much as it is a right. Use it wisely.",
    "AvailabilityQuest4Id": -1,
    "AvailabilityQuest3Id": -1,
    "AvailabilityQuest2Id": -1,
    "AvailabilityDialog2Id": -1,
    "AvailabilityDialog3Id": -1,
    "AvailabilityDialog4Id": -1,
    "AvailabilityMinPlayerLevel": 0,
    "DecreaseFaction2Points": 0b,
    "DialogMail": {
        "Sender": "",
        "BeenRead": 0b,
        "Message": {
        },
        "MailItems": [
        ],
        "MailQuest": -1,
        "TimePast": 1723025600936L,
        "Time": 0L,
        "Subject": ""
    }
}
